[
  {
    "id": "1767185214167",
    "title": "kk",
    "content": "kk"
  },
  {
    "id": "1767185360643",
    "title": "aaa",
    "content": "aaa"
  },
  {
    "id": "1767185363263",
    "title": "aaa",
    "content": "aa"
  },
  {
    "id": "1767185390956",
    "title": "aley",
    "content": ""
  },
  {
    "id": "1767185421649",
    "title": "aaa",
    "content": "sasa",
    "owner": "aleyy"
  },
  {
    "id": "1767185422530",
    "title": "",
    "content": "",
    "owner": "aleyy"
  },
  {
    "id": "1767185422879",
    "title": "",
    "content": "",
    "owner": "aleyy"
  },
  {
    "id": "1767185426729",
    "title": "sadllsad",
    "content": "sdkkd",
    "owner": "aleyy"
  },
  {
    "id": "1767185427030",
    "title": "",
    "content": "",
    "owner": "aleyy"
  },
  {
    "id": "1767185427213",
    "title": "",
    "content": "",
    "owner": "aleyy"
  },
  {
    "id": "1767185427378",
    "title": "",
    "content": "",
    "owner": "aleyy"
  },
  {
    "id": "1767185427546",
    "title": "",
    "content": "",
    "owner": "aleyy"
  },
  {
    "id": "1767185427713",
    "title": "",
    "content": "",
    "owner": "aleyy"
  },
  {
    "id": "1767185427878",
    "title": "",
    "content": "",
    "owner": "aleyy"
  },
  {
    "id": "1767185428047",
    "title": "",
    "content": "",
    "owner": "aleyy"
  },
  {
    "id": "1767185428196",
    "title": "",
    "content": "",
    "owner": "aleyy"
  },
  {
    "id": "1767185428380",
    "title": "",
    "content": "",
    "owner": "aleyy"
  },
  {
    "id": "1767185921561",
    "title": "1.güm",
    "content": "skjsjk",
    "owner": "ayse"
  },
  {
    "id": "1767185925677",
    "title": "2.gün",
    "content": "ssa",
    "owner": "ayse"
  },
  {
    "id": "1767185932877",
    "title": "sss",
    "content": "sss",
    "owner": "aysee"
  },
  {
    "id": "1767185935512",
    "title": "aksi",
    "content": "sdksakd",
    "owner": "aysee"
  },
  {
    "id": "1767185947210",
    "title": "ekeke",
    "content": "kod ck",
    "owner": "aysee"
  }
]